kubernetes-stubs/__init__.pyi
kubernetes-stubs/client/__init__.pyi
kubernetes-stubs/client/api/WellKnown_api.pyi
kubernetes-stubs/client/api/__init__.pyi
kubernetes-stubs/client/api/admissionregistration_api.pyi
kubernetes-stubs/client/api/admissionregistration_v1_api.pyi
kubernetes-stubs/client/api/admissionregistration_v1alpha1_api.pyi
kubernetes-stubs/client/api/admissionregistration_v1beta1_api.pyi
kubernetes-stubs/client/api/apiextensions_api.pyi
kubernetes-stubs/client/api/apiextensions_v1_api.pyi
kubernetes-stubs/client/api/apiregistration_api.pyi
kubernetes-stubs/client/api/apiregistration_v1_api.pyi
kubernetes-stubs/client/api/apis_api.pyi
kubernetes-stubs/client/api/apps_api.pyi
kubernetes-stubs/client/api/apps_v1_api.pyi
kubernetes-stubs/client/api/authentication_api.pyi
kubernetes-stubs/client/api/authentication_v1_api.pyi
kubernetes-stubs/client/api/authorization_api.pyi
kubernetes-stubs/client/api/authorization_v1_api.pyi
kubernetes-stubs/client/api/autoscaling_api.pyi
kubernetes-stubs/client/api/autoscaling_v1_api.pyi
kubernetes-stubs/client/api/autoscaling_v2_api.pyi
kubernetes-stubs/client/api/batch_api.pyi
kubernetes-stubs/client/api/batch_v1_api.pyi
kubernetes-stubs/client/api/certificates_api.pyi
kubernetes-stubs/client/api/certificates_v1_api.pyi
kubernetes-stubs/client/api/certificates_v1alpha1_api.pyi
kubernetes-stubs/client/api/certificates_v1beta1_api.pyi
kubernetes-stubs/client/api/coordination_api.pyi
kubernetes-stubs/client/api/coordination_v1_api.pyi
kubernetes-stubs/client/api/coordination_v1alpha2_api.pyi
kubernetes-stubs/client/api/coordination_v1beta1_api.pyi
kubernetes-stubs/client/api/core_api.pyi
kubernetes-stubs/client/api/core_v1_api.pyi
kubernetes-stubs/client/api/custom_objects_api.pyi
kubernetes-stubs/client/api/discovery_api.pyi
kubernetes-stubs/client/api/discovery_v1_api.pyi
kubernetes-stubs/client/api/events_api.pyi
kubernetes-stubs/client/api/events_v1_api.pyi
kubernetes-stubs/client/api/flowcontrolApiserver_api.pyi
kubernetes_stubs_elephant_fork-34.1.0.dist-info/WHEEL
kubernetes_stubs_elephant_fork-34.1.0.dist-info/METADATA
kubernetes_stubs_elephant_fork-34.1.0.dist-info/RECORD
