Metadata-Version: 2.1
Name: kubernetes-stubs-elephant-fork
Version: 34.1.0
Summary: Type stubs for the Kubernetes Python API client
Home-page: https://github.com/lexdene/kubernetes-stubs
License: Apache-2.0
Author: Nikhil Benesch
Author-email: nikhil.benesch@gmail.com
Classifier: License :: OSI Approved :: Apache Software License
Classifier: Programming Language :: Python :: 2
Classifier: Programming Language :: Python :: 2.7
Classifier: Programming Language :: Python :: 3
Classifier: Programming Language :: Python :: 3.4
Classifier: Programming Language :: Python :: 3.5
Classifier: Programming Language :: Python :: 3.6
Classifier: Programming Language :: Python :: 3.7
Classifier: Programming Language :: Python :: 3.8
Classifier: Programming Language :: Python :: 3.9
Classifier: Programming Language :: Python :: 3.10
Classifier: Programming Language :: Python :: 3.11
